odinweb/__init__.py
odinweb/api.py
odinweb/constants.py
odinweb/containers.py
odinweb/content_type_resolvers.py
odinweb/cors.py
odinweb/data_structures.py
odinweb/decorators.py
odinweb/doc.py
odinweb/exceptions.py
odinweb/helpers.py
odinweb/oauth.py
odinweb/resources.py
odinweb/signing.py
odinweb/swagger.py
odinweb/testing.py
odinweb/utils.py
odinweb/_compat/__init__.py
odinweb/_compat/http.py
odinweb/middleware/__init__.py
odinweb/middleware/cors.py
odinweb/middleware/oauth.py
odinweb/middleware/signing.py
odinweb/static/bundle.js
odinweb/static/standalone-preset.js
odinweb/static/ui.css
odinweb/static/ui.html
odinweb-0.5.2.dist-info/DESCRIPTION.rst
odinweb-0.5.2.dist-info/METADATA
odinweb-0.5.2.dist-info/RECORD
odinweb-0.5.2.dist-info/WHEEL
odinweb-0.5.2.dist-info/metadata.json
odinweb-0.5.2.dist-info/pbr.json
odinweb-0.5.2.dist-info/top_level.txt
