Metadata-Version: 2.0
Name: odinweb
Version: 0.5.2
Summary: Toolkit for building web API's using Odin
Home-page: https://github.com/python-odin/odinweb
Author: Tim Savage
Author-email: tim@savage.company
License: BSD
Keywords: web
Requires-Dist: odin (>=1.4.0)
Requires-Dist: typing; (python_version == '2.7')
Requires-Dist: enum34; (python_version == '2.7')
